imc/__init__.py
imc/_version.py
imc/cli.py
imc/defaults.py
imc/exceptions.py
imc/graphics.py
imc/interactive_volume_viewer.py
imc/logo.png
imc/py.typed
imc/segmentation.py
imc/types.py
imc/utils.py
imc/data_models/__init__.py
imc/data_models/project.py
imc/data_models/roi.py
imc/data_models/sample.py
imc/demo/__init__.py
imc/demo/generate_data.py
imc/demo/get_demo_data.py
imc/ops/__init__.py
imc/ops/adjacency.py
imc/ops/clustering.py
imc/ops/community.py
imc/ops/compensation.py
imc/ops/domain.py
imc/ops/mixture.py
imc/ops/quant.py
imc/ops/signal.py
imc/scripts/__init__.py
imc/scripts/illustrate.py
imc/scripts/inspect_ilastik_model.py
imc/scripts/inspect_mcds.py
imc/scripts/phenotype.py
imc/scripts/predict.py
imc/scripts/prepare.py
imc/scripts/process.py
imc/scripts/quantify.py
imc/scripts/segment_stacks.py
imc/scripts/view.py
imc/tests/__init__.py
imc/tests/_test_layers.py
imc/tests/conftest.py
imc/tests/test_full_analysis.py
imc/tests/test_graphics.py
imc/tests/test_obj_creation.py
imc/tests/test_serialization.py
imc-0.1.4.dist-info/METADATA
imc-0.1.4.dist-info/WHEEL
imc-0.1.4.dist-info/entry_points.txt
imc-0.1.4.dist-info/top_level.txt
imc-0.1.4.dist-info/RECORD
